{
  "igVal": 1.06,
  "t10y2yVal": 0.39,
  "aaaOasVal": 0.34,
  "hyVal": 2.78,
  "ismVal": 0.0,
  "vixVal": 17.68,
  "vxnVal": 27.27,
  "capeVal": 36.6,
  "cpiVal": 333.979,
  "t10yVal": 4.45,
  "brentVal": 87.33,
  "status": "極端風險",
  "aiContent": "景氣解讀與投資策略建議\n\n大項 1: 景氣解讀\n\n1.  經濟面臨史無前例的超高通膨危機\n       理由: 消費者物價指數 (CPI) 高達333.979%，這是一個極端且毀滅性的通膨數據，遠超正常經濟增長範圍，暗示經濟已陷入惡性通膨（hyperinflation）狀態。此狀況將嚴重侵蝕購買力，打擊企業獲利，並可能導致社會經濟秩序混亂，是系統判定為「極端風險」的最核心且直接的理由。\n       相關數據: Brent原油價格維持在87.33$的高位，反映了全球能源需求或供應端壓力，進一步加劇了通膨形勢。美國10年期公債殖利率達到4.45%，也部分反映了市場對持續高通膨的預期。\n\n2.  市場情緒與信用風險指標出現異常矛盾\n       理由: VIX恐慌指數為17.68，處於相對平靜的水平（低於20），並未顯示市場有顯著的恐慌情緒。同時，AAA等級債券的選擇權調整利差 (AAA OAS) 僅0.34%，高收益債券的選擇權調整利差 (HY OAS) 也僅2.78%，這些信用利差水準歷史上偏低，通常意味著市場對企業違約風險的擔憂不大。這些數據與「極端風險」的系統判定存在顯著矛盾，可能暗示市場尚未完全消化超高通膨所帶來的嚴重經濟衝擊及潛在風險。\n       相關數據: VXN納斯達克100指數波動率為27.27，雖略高於VIX，顯示科技板塊波動較大，但整體市場情緒仍未達恐慌級別。10Y-2Y公債利差為0.39%，維持正值，通常不被視為衰退預警，這也與極端風險的判斷形成對比。\n\n3.  股市估值處於歷史高位，存在潛在修正風險\n       理由: 景氣循環調整本益比 (CAPE) 高達36.6倍，顯示整體股市估值在歷史上屬於非常昂貴的區間。儘管市場情緒未見恐慌，但高估值在超高通膨和潛在經濟困境的背景下，面臨巨大的修正壓力。\n\n大項 2: 投資策略建議\n\n1.  採取「左肩交易」策略\n       理由: 儘管VIX指數17.68尚未達到30的極端恐慌閾值，但鑒於系統已明確判定為「極端風險」，且宏觀經濟數據（特別是CPI高達333.979%）已構成實質上的「極端恐慌」經濟環境。面對如此嚴峻的基本面風險，應預防性地採取「左肩交易」策略，為市場可能出現的劇烈下跌做準備。\n       具體作法:\n        1.  分批資金控管: 嚴格控制每次投入的資金比例，避免在單一時間點或單一資產上過度集中，保留充足的現金流以應對未來的市場不確定性。\n        2.  跌幅加碼級距: 預設明確的市場下跌幅度，例如每當市場指數下跌特定百分比時，按照預定比例增加投資部位。此策略旨在逢低佈局，有效降低平均成本，為市場恢復後的反彈做好準備。\n\n2.  維持降槓桿策略\n       理由: 雖然VIX指數17.68尚未達到低於15的「過度樂觀」區間，但當前市場的CAPE估值高達36.6倍，已是歷史上非常高的水平，且經濟正承受史無前例的超高通膨壓力。在高估值和極端通膨的雙重風險下，任何形式的槓桿都將大幅放大投資組合的潛在虧損。因此，為防範系統性風險，主動降低槓桿水平，保護資本，是當前極端風險環境下至關重要且審慎的風險管理措施。\n\n3.  配置防禦部位：BOXX ETF\n       理由: 在當前超高通膨、市場估值高且存在極端風險的環境下，配置具防禦性質的資產至關重要。BOXX ETF旨在透過複製美國國庫券的收益，並運用選擇權策略來實現稅務效率。其特點是波動性較低，能提供穩定的現金回報，且在稅務上具備優勢（將部分收益轉換為符合資格的股利）。將BOXX ETF納入防禦部位，不僅能作為現金的替代品，提供流動性和穩健收益，幫助抵禦部分通膨侵蝕，還能在市場震盪時提供相對穩定的資產避風港，符合在極端風險時期保護資本的需求。",
  "timestamp": "2026/06/13 23:37:04"
}